demo/__init__.py
flaskerize/__init__.py
flaskerize/attach.py
flaskerize/attach_test.py
flaskerize/custom_functions.py
flaskerize/custom_functions_test.py
flaskerize/exceptions.py
flaskerize/fileio.py
flaskerize/fileio_test.py
flaskerize/generate.py
flaskerize/generate_test.py
flaskerize/parser.py
flaskerize/parser_test.py
flaskerize/render.py
flaskerize/render_test.py
flaskerize/utils.py
flaskerize/utils_test.py
flaskerize/__pycache__/__init__.cpython-37.pyc
flaskerize/__pycache__/attach.cpython-37.pyc
flaskerize/__pycache__/attach_test.cpython-37-pytest-5.0.1.pyc
flaskerize/__pycache__/attach_test.cpython-37-pytest-5.3.2.pyc
flaskerize/__pycache__/attach_test.cpython-37-pytest-5.3.4.pyc
flaskerize/__pycache__/custom_functions.cpython-37-pytest-5.0.1.pyc
flaskerize/__pycache__/custom_functions.cpython-37.pyc
flaskerize/__pycache__/custom_functions_test.cpython-37-pytest-5.0.1.pyc
flaskerize/__pycache__/custom_functions_test.cpython-37-pytest-5.3.2.pyc
flaskerize/__pycache__/custom_functions_test.cpython-37-pytest-5.3.4.pyc
flaskerize/__pycache__/exceptions.cpython-37.pyc
flaskerize/__pycache__/fileio.cpython-37-pytest-5.0.1.pyc
flaskerize/__pycache__/fileio.cpython-37.pyc
flaskerize/__pycache__/fileio_test.cpython-37-pytest-5.0.1.pyc
flaskerize/__pycache__/fileio_test.cpython-37-pytest-5.3.2.pyc
flaskerize/__pycache__/fileio_test.cpython-37-pytest-5.3.4.pyc
flaskerize/__pycache__/fs.cpython-37.pyc
flaskerize/__pycache__/fs_test.cpython-37-pytest-5.0.1.pyc
flaskerize/__pycache__/generate.cpython-37.pyc
flaskerize/__pycache__/generate_test.cpython-37-pytest-5.0.1.pyc
flaskerize/__pycache__/generate_test.cpython-37-pytest-5.3.2.pyc
flaskerize/__pycache__/generate_test.cpython-37-pytest-5.3.4.pyc
flaskerize/__pycache__/parser.cpython-37.pyc
flaskerize/__pycache__/parser_test.cpython-37-pytest-5.0.1.pyc
flaskerize/__pycache__/parser_test.cpython-37-pytest-5.3.2.pyc
flaskerize/__pycache__/parser_test.cpython-37-pytest-5.3.4.pyc
flaskerize-0.14.0.dist-info/LICENSE
flaskerize-0.14.0.dist-info/METADATA
flaskerize-0.14.0.dist-info/WHEEL
flaskerize-0.14.0.dist-info/top_level.txt
flaskerize-0.14.0.dist-info/RECORD
