Metadata-Version: 1.0
Name: flaskerize
Version: 0.14.0
Summary: Python CLI build/dev tool for templated code generation and project modification. Think Angular schematics for Python.
Home-page: http://alanpryorjr.com/
Author: AJ Pryor
Author-email: apryor6@gmail.com
License: UNKNOWN
Platform: UNKNOWN
